Metadata-Version: 2.1
Name: meu-pacote-mab
Version: 0.0.1
Requires-Dist: httpx
